{
  "Cardiologia": {
    "Dr. Teresa Serrano": ["19/2    08:30", "1/7    11:30", "12/4    13:00", "4/7    07:00", "23/9    08:00", "13/9    07:30", "14/3    08:00", "29/11    12:30", "22/1    13:30", "2/3    08:00"],
    "Dr. Silvia Ramos": ["19/2    08:30", "1/7    11:30", "12/4    13:00", "4/7    07:00", "23/9    08:00", "13/9    07:30", "14/3    08:00", "29/11    12:30", "22/1    13:30", "2/3    08:00"],
    "Dr. Manuel García": ["19/2    08:30", "1/7    11:30", "12/4    13:00", "4/7    07:00", "23/9    08:00", "13/9    07:30", "14/3    08:00", "29/11    12:30", "22/1    13:30", "2/3    08:00"],
    "Dr. Sergio Aguilar": ["19/2    08:30", "1/7    11:30", "12/4    13:00", "4/7    07:00", "23/9    08:00", "13/9    07:30", "14/3    08:00", "29/11    12:30", "22/1    13:30", "2/3    08:00"],
    "Dr. Alejandro Silva": ["19/2    08:30", "1/7    11:30", "12/4    13:00", "4/7    07:00", "23/9    08:00", "13/9    07:30", "14/3    08:00", "29/11    12:30", "22/1    13:30", "2/3    08:00"]
  },
  "Dermatologia": {
    "Dr. Diego Núñez": ["20/5    09:30", "9/8    10:30", "20/6    14:30", "7/6    12:00", "17/6    11:30", "21/2    08:30", "22/4    07:30", "28/3    13:30", "9/7    13:00", "30/10    12:30"],
    "Dr. Catalina Silva": ["20/5    09:30", "9/8    10:30", "20/6    14:30", "7/6    12:00", "17/6    11:30", "21/2    08:30", "22/4    07:30", "28/3    13:30", "9/7    13:00", "30/10    12:30"],
    "Dr. Gabriela Acosta": ["20/5    09:30", "9/8    10:30", "20/6    14:30", "7/6    12:00", "17/6    11:30", "21/2    08:30", "22/4    07:30", "28/3    13:30", "9/7    13:00", "30/10    12:30"],
    "Dr. Héctor López": ["20/5    09:30", "9/8    10:30", "20/6    14:30", "7/6    12:00", "17/6    11:30", "21/2    08:30", "22/4    07:30", "28/3    13:30", "9/7    13:00", "30/10    12:30"],
    "Dr. Patricia Torres": ["20/5    09:30", "9/8    10:30", "20/6    14:30", "7/6    12:00", "17/6    11:30", "21/2    08:30", "22/4    07:30", "28/3    13:30", "9/7    13:00", "30/10    12:30"]
  },
  "Cirugia General": {
    "Dr. Liliana Blanco": ["2/6    09:00", "30/1    12:00", "13/3    11:30", "20/6    11:00", "18/6    10:00", "18/1    10:00", "4/7    11:00", "27/11    08:00", "3/12    11:00", "20/5    14:30"],
    "Dr. Gloria Vega": ["2/6    09:00", "30/1    12:00", "13/3    11:30", "20/6    11:00", "18/6    10:00", "18/1    10:00", "4/7    11:00", "27/11    08:00", "3/12    11:00", "20/5    14:30"],
    "Dr. Juan Pérez": ["2/6    09:00", "30/1    12:00", "13/3    11:30", "20/6    11:00", "18/6    10:00", "18/1    10:00", "4/7    11:00", "27/11    08:00", "3/12    11:00", "20/5    14:30"],
    "Dr. Claudia Peña": ["2/6    09:00", "30/1    12:00", "13/3    11:30", "20/6    11:00", "18/6    10:00", "18/1    10:00", "4/7    11:00", "27/11    08:00", "3/12    11:00", "20/5    14:30"],
    "Dr. Iván Aguilera": ["2/6    09:00", "30/1    12:00", "13/3    11:30", "20/6    11:00", "18/6    10:00", "18/1    10:00", "4/7    11:00", "27/11    08:00", "3/12    11:00", "20/5    14:30"]
  },
  "Endocrinologia": {
    "Dr. Eduardo Muñoz": ["15/8    12:30", "20/1    08:00", "17/1    13:30", "13/9    07:00", "3/12    14:30", "9/12    07:30", "27/12    10:00", "13/6    08:00", "30/8    09:00", "15/6    14:30"],
    "Dr. Ricardo Soto": ["15/8    12:30", "20/1    08:00", "17/1    13:30", "13/9    07:00", "3/12    14:30", "9/12    07:30", "27/12    10:00", "13/6    08:00", "30/8    09:00", "15/6    14:30"],
    "Dr. José Hernández": ["15/8    12:30", "20/1    08:00", "17/1    13:30", "13/9    07:00", "3/12    14:30", "9/12    07:30", "27/12    10:00", "13/6    08:00", "30/8    09:00", "15/6    14:30"],
    "Dr. Daniela Mendoza": ["15/8    12:30", "20/1    08:00", "17/1    13:30", "13/9    07:00", "3/12    14:30", "9/12    07:30", "27/12    10:00", "13/6    08:00", "30/8    09:00", "15/6    14:30"],
    "Dr. Raúl Rivas": ["15/8    12:30", "20/1    08:00", "17/1    13:30", "13/9    07:00", "3/12    14:30", "9/12    07:30", "27/12    10:00", "13/6    08:00", "30/8    09:00", "15/6    14:30"]
  },
  "Gastroenterologia": {
    "Dr. Valentina Morales": ["23/1    12:30", "26/7    08:00", "20/12    11:30", "18/5    13:30", "17/10    07:30", "20/6    11:30", "27/4    08:30", "4/1    07:00", "7/8    07:30", "1/1    07:00"],
    "Dr. Pilar Ponce": ["23/1    12:30", "26/7    08:00", "20/12    11:30", "18/5    13:30", "17/10    07:30", "20/6    11:30", "27/4    08:30", "4/1    07:00", "7/8    07:30", "1/1    07:00"],
    "Dr. Emilio Torres": ["23/1    12:30", "26/7    08:00", "20/12    11:30", "18/5    13:30", "17/10    07:30", "20/6    11:30", "27/4    08:30", "4/1    07:00", "7/8    07:30", "1/1    07:00"],
    "Dr. Marcos Gutiérrez": ["23/1    12:30", "26/7    08:00", "20/12    11:30", "18/5    13:30", "17/10    07:30", "20/6    11:30", "27/4    08:30", "4/1    07:00", "7/8    07:30", "1/1    07:00"],
    "Dr. Mónica Gallardo": ["23/1    12:30", "26/7    08:00", "20/12    11:30", "18/5    13:30", "17/10    07:30", "20/6    11:30", "27/4    08:30", "4/1    07:00", "7/8    07:30", "1/1    07:00"]
  },
  "Ginecologia": {
    "Dr. Alberto Sánchez": ["15/5    14:00", "17/8    11:30", "12/1    09:30", "5/8    10:30", "7/8    13:00", "12/4    09:00", "30/12    10:00", "11/7    14:00", "18/5    08:30", "31/7    12:00"],
    "Dr. Lucía Castro": ["15/5    14:00", "17/8    11:30", "12/1    09:30", "5/8    10:30", "7/8    13:00", "12/4    09:00", "30/12    10:00", "11/7    14:00", "18/5    08:30", "31/7    12:00"],
    "Dr. Jorge Romero": ["15/5    14:00", "17/8    11:30", "12/1    09:30", "5/8    10:30", "7/8    13:00", "12/4    09:00", "30/12    10:00", "11/7    14:00", "18/5    08:30", "31/7    12:00"],
    "Dr. Camila Rodríguez": ["15/5    14:00", "17/8    11:30", "12/1    09:30", "5/8    10:30", "7/8    13:00", "12/4    09:00", "30/12    10:00", "11/7    14:00", "18/5    08:30", "31/7    12:00"],
    "Dr. Adriana Reyes": ["15/5    14:00", "17/8    11:30", "12/1    09:30", "5/8    10:30", "7/8    13:00", "12/4    09:00", "30/12    10:00", "11/7    14:00", "18/5    08:30", "31/7    12:00"]
  },
  "Neumonologia": {
    "Dr. Francisco Paredes": ["25/12    16:00", "3/6    20:30", "28/5    21:30", "1/11    19:00", "27/3    21:00", "10/9    19:30", "22/12    22:30", "24/3    19:00", "23/9    15:00", "27/2    16:00"],
    "Dr. Francisco Núñez": ["25/12    16:00", "3/6    20:30", "28/5    21:30", "1/11    19:00", "27/3    21:00", "10/9    19:30", "22/12    22:30", "24/3    19:00", "23/9    15:00", "27/2    16:00"],
    "Dr. Verónica Flores": ["25/12    16:00", "3/6    20:30", "28/5    21:30", "1/11    19:00", "27/3    21:00", "10/9    19:30", "22/12    22:30", "24/3    19:00", "23/9    15:00", "27/2    16:00"],
    "Dr. Estefanía Ruiz": ["25/12    16:00", "3/6    20:30", "28/5    21:30", "1/11    19:00", "27/3    21:00", "10/9    19:30", "22/12    22:30", "24/3    19:00", "23/9    15:00", "27/2    16:00"],
    "Dr. Ramón Herrera": ["25/12    16:00", "3/6    20:30", "28/5    21:30", "1/11    19:00", "27/3    21:00", "10/9    19:30", "22/12    22:30", "24/3    19:00", "23/9    15:00", "27/2    16:00"]
  },
  "Neurocirugia": {
    "Dr. Elisa Serrano": ["26/3    22:00", "14/2    21:00", "14/5    19:00", "6/7    18:00", "2/4    18:00", "29/11    17:00", "2/1    21:00", "6/2    18:30", "14/1    17:30", "17/8    18:00"],
    "Dr. Natalia Salazar": ["26/3    22:00", "14/2    21:00", "14/5    19:00", "6/7    18:00", "2/4    18:00", "29/11    17:00", "2/1    21:00", "6/2    18:30", "14/1    17:30", "17/8    18:00"],
    "Dr. Claudia Guzmán": ["26/3    22:00", "14/2    21:00", "14/5    19:00", "6/7    18:00", "2/4    18:00", "29/11    17:00", "2/1    21:00", "6/2    18:30", "14/1    17:30", "17/8    18:00"],
    "Dr. Carlos Ramírez": ["26/3    22:00", "14/2    21:00", "14/5    19:00", "6/7    18:00", "2/4    18:00", "29/11    17:00", "2/1    21:00", "6/2    18:30", "14/1    17:30", "17/8    18:00"],
    "Dr. Beatriz Vargas": ["26/3    22:00", "14/2    21:00", "14/5    19:00", "6/7    18:00", "2/4    18:00", "29/11    17:00", "2/1    21:00", "6/2    18:30", "14/1    17:30", "17/8    18:00"]
  },
  "Oftalmologia": {
    "Dr. Roberto Medina": ["7/12    18:30", "26/2    15:30", "6/3    19:00", "23/9    20:30", "1/7    20:00", "5/8    19:30", "18/1    15:30", "20/4    17:00", "5/3    20:30", "27/1    16:00"],
    "Dr. Luis Fernández": ["7/12    18:30", "26/2    15:30", "6/3    19:00", "23/9    20:30", "1/7    20:00", "5/8    19:30", "18/1    15:30", "20/4    17:00", "5/3    20:30", "27/1    16:00"],
    "Dr. Gabriela Castillo": ["7/12    18:30", "26/2    15:30", "6/3    19:00", "23/9    20:30", "1/7    20:00", "5/8    19:30", "18/1    15:30", "20/4    17:00", "5/3    20:30", "27/1    16:00"],
    "Dr. Andrés Flores": ["7/12    18:30", "26/2    15:30", "6/3    19:00", "23/9    20:30", "1/7    20:00", "5/8    19:30", "18/1    15:30", "20/4    17:00", "5/3    20:30", "27/1    16:00"],
    "Dr. Ingrid Ortega": ["7/12    18:30", "26/2    15:30", "6/3    19:00", "23/9    20:30", "1/7    20:00", "5/8    19:30", "18/1    15:30", "20/4    17:00", "5/3    20:30", "27/1    16:00"]
  },
  "Pediatria": {
    "Dr. Javier Pérez": ["20/10    22:30", "21/2    16:30", "27/2    22:00", "30/9    17:30", "29/8    19:00", "23/5    21:30", "8/12    22:30", "18/9    17:00", "20/2    20:00", "2/10    21:00"],
    "Dr. Sergio Gómez": ["20/10    22:30", "21/2    16:30", "27/2    22:00", "30/9    17:30", "29/8    19:00", "23/5    21:30", "8/12    22:30", "18/9    17:00", "20/2    20:00", "2/10    21:00"],
    "Dr. Ricardo Fernández": ["20/10    22:30", "21/2    16:30", "27/2    22:00", "30/9    17:30", "29/8    19:00", "23/5    21:30", "8/12    22:30", "18/9    17:00", "20/2    20:00", "2/10    21:00"],
    "Dr. María González": ["20/10    22:30", "21/2    16:30", "27/2    22:00", "30/9    17:30", "29/8    19:00", "23/5    21:30", "8/12    22:30", "18/9    17:00", "20/2    20:00", "2/10    21:00"],
    "Dr. Ana Martínez": ["20/10    22:30", "21/2    16:30", "27/2    22:00", "30/9    17:30", "29/8    19:00", "23/5    21:30", "8/12    22:30", "18/9    17:00", "20/2    20:00", "2/10    21:00"]
  },
  "Psiquiatria": {
    "Dr. Óscar Benítez": ["20/10    21:30", "28/7    22:00", "12/5    17:00", "4/4    15:30", "6/8    18:30", "26/7    22:00", "5/11    21:30", "28/10    21:00", "23/5    16:00", "7/6    22:30"],
    "Dr. Esteban Castillo": ["20/10    21:30", "28/7    22:00", "12/5    17:00", "4/4    15:30", "6/8    18:30", "26/7    22:00", "5/11    21:30", "28/10    21:00", "23/5    16:00", "7/6    22:30"],
    "Dr. Susana Castro": ["20/10    21:30", "28/7    22:00", "12/5    17:00", "4/4    15:30", "6/8    18:30", "26/7    22:00", "5/11    21:30", "28/10    21:00", "23/5    16:00", "7/6    22:30"],
    "Dr. Elena Díaz": ["20/10    21:30", "28/7    22:00", "12/5    17:00", "4/4    15:30", "6/8    18:30", "26/7    22:00", "5/11    21:30", "28/10    21:00", "23/5    16:00", "7/6    22:30"],
    "Dr. Antonio Jiménez": ["20/10    21:30", "28/7    22:00", "12/5    17:00", "4/4    15:30", "6/8    18:30", "26/7    22:00", "5/11    21:30", "28/10    21:00", "23/5    16:00", "7/6    22:30"]
  },
  "Traumatologia": {
    "Dr. Miguel Reyes": ["16/3    18:00", "29/12    22:00", "14/1    19:30", "27/4    20:00", "26/8    17:00", "7/1    22:00", "24/7    21:30", "4/6    15:30", "28/5    18:00", "5/6    19:30"],
    "Dr. Carmen Ortiz": ["16/3    18:00", "29/12    22:00", "14/1    19:30", "27/4    20:00", "26/8    17:00", "7/1    22:00", "24/7    21:30", "4/6    15:30", "28/5    18:00", "5/6    19:30"],
    "Dr. Andrés Moreno": ["16/3    18:00", "29/12    22:00", "14/1    19:30", "27/4    20:00", "26/8    17:00", "7/1    22:00", "24/7    21:30", "4/6    15:30", "28/5    18:00", "5/6    19:30"],
    "Dr. Laura López": ["16/3    18:00", "29/12    22:00", "14/1    19:30", "27/4    20:00", "26/8    17:00", "7/1    22:00", "24/7    21:30", "4/6    15:30", "28/5    18:00", "5/6    19:30"],
    "Dr. Martín Muñoz": ["16/3    18:00", "29/12    22:00", "14/1    19:30", "27/4    20:00", "26/8    17:00", "7/1    22:00", "24/7    21:30", "4/6    15:30", "28/5    18:00", "5/6    19:30"]
  }
}
